infoplus/__init__.py
infoplus/MindSporeInfoPlus/__init__.py
infoplus/MindSporeInfoPlus/enums.py
infoplus/MindSporeInfoPlus/formatting.py
infoplus/MindSporeInfoPlus/layer_info.py
infoplus/MindSporeInfoPlus/mindsporeinfoplus.py
infoplus/MindSporeInfoPlus/model_statistics.py
infoplus/TorchInfoPlus/__init__.py
infoplus/TorchInfoPlus/enums.py
infoplus/TorchInfoPlus/formatting.py
infoplus/TorchInfoPlus/layer_info.py
infoplus/TorchInfoPlus/model_statistics.py
infoplus/TorchInfoPlus/torchinfoplus.py
infoplus-0.0.2.dist-info/LICENSE
infoplus-0.0.2.dist-info/METADATA
infoplus-0.0.2.dist-info/WHEEL
infoplus-0.0.2.dist-info/top_level.txt
infoplus-0.0.2.dist-info/RECORD
